Team19CustomUtils/__init__.py
Team19CustomUtils/generalUtils.py
Team19CustomUtils/imageUtils.py
Team19CustomUtils/mlUtils.py
Team19CustomUtils/proceduralTree.py
team_19_custom_utils_lib-0.1.5.13.dist-info/licenses/LICENSE
team_19_custom_utils_lib-0.1.5.13.dist-info/METADATA
team_19_custom_utils_lib-0.1.5.13.dist-info/WHEEL
team_19_custom_utils_lib-0.1.5.13.dist-info/top_level.txt
team_19_custom_utils_lib-0.1.5.13.dist-info/RECORD
