Metadata-Version: 2.4
Name: Team_19_Custom_Utils_Lib
Version: 0.1.5.13
Summary: Custom package for ENGR 133 team 19, Fall 2025 semester
Author-email: Mark Sheng <marksheng2020@example.com>
License-Expression: MIT
Project-URL: Homepage, https://github.com/someone225/School-work
Project-URL: Issues, https://github.com/someone225/School-work/issues
Classifier: Programming Language :: Python :: 3
Classifier: Operating System :: OS Independent
Requires-Python: >=3.9
License-File: LICENSE
Dynamic: license-file
